{
    "skills": "Contract drafting & Negotiation, IT Vendor Procurement and Regulatory Compliance, Agile process control and implementation, Enterprise-wide software and contract administration, Technology budget management, Risk management, Process improvements, Critical thinking, Implementing new processes, Business Systems Consulting, Business Systems Analysis, Contract Negotiations, Vendor Management, Compliance Management, Supplier Relationship Management, Negotiation and Conflict Resolution, Strategic Sourcing, Contract Administration, Contract Review, Legal Contract Drafting, Contract Management, Software Licensing, IT Compliance, IT Purchasing, Pricing Analysis, Market Research, Proposal Management, Sales Forecasting, RFP Management, Salesforce.com, Microsoft Office Suite 2019, MS Project, ServiceNow, Ariba, SalesForce.com, SharePoint, Adobe, DocuSign, SAP, Maximo, Oracle, VISIO, NetSuite, COUPA, LexisNexis, Amicus, Schedule Plus, PeopleSoft",
    "education": "[\"Edu1\":{\"degree\":\"BS\",\"university\":\"Shorter University\",\"graduationDate\":null},\n\"Edu2\":{\"degree\":\"Paralegal Certificate\",\"university\":\"Kennesaw State University\",\"graduationDate\":null},\n\"Edu3\":{\"degree\":\"PMP Certificate\",\"university\":\"Comnet Group, Inc.\",\"graduationDate\":null}]",
    "work_exp": "[{\"name\":\"NetApp, Inc.\"},{\"name\":\"TIAA Bank\"},{\"name\":\"Wells Fargo Company\"},{\"name\":\"Ingersoll Rand Company\"},{\"name\":\"Duke Energy Corporation\"},{\"name\":\"Genuine Parts Company\"},{\"name\":\"Dell SecureWorks\"},{\"name\":\"The Home Depot, Inc.\"}]",
    "personal_info": "[{\"Name\":\"Sharon Davis\", \"ID\":\"P1\", \"Email\":\"ad39mo@r.postjobfree.com\"}]",
    "volunteer_info": "No volunteer experience found."
}