{
    "skills": "Testing Tools: Selenium WebDriver, Visual Studios team Suits (VSTS), TFS, Appium, Postman, Soup UI\nLanguages: Python, JAVA, C#.Net, HTML, XML, PL/SQL\nWeb Technologies: HTML, XML, CSS, DHTML, Angular JS, Node.JS\nIDE: Visual Studio code, PyCharm, Eclipse, SQL Developer\nTest Framework: Test Driven, TestNG, Data Driven Framework\nWeb Debugging Tool: Fire path, Firebug\nBuild Tool: Ant, Maven\nProcesses: Agile-Scrum, Waterfall\nBug Tracking Tools: JIRA, Quality Center (QC), Bugzilla & IBM Rational Team Concert (RTC), Q-Test\nContinuous Integration Tools: Jenkins\nVersion Control: GIT\nData Bases: MS Access, Oracle, MySQL, NO SQL DATABASE\nCloud Platform: AWS (EC2, S3, VPC, ELB)\nOperating Systems: Windows (XP, Vista & 7, 8), Unix, Linux, Mac",
    "education": "No education-related information is present in the provided text. Hence, the list of education entities is empty.",
    "work_exp": "[{\"name\":\"T-Mobile\"},{\"name\":\"Republic Services\"},{\"name\":\"Equifax INC\"},{\"name\":\"Nielsen\"}]",
    "personal_info": "[\n    {\n        \"label\":\"Person\",\n        \"ID\":\"001\",\n        \"Email\":\"ad4id4@r.postjobfree.com\"\n    }\n]",
    "volunteer_info": "No volunteer work entities found."
}