{
    "skills": "AutoCAD 2010, PLC, Scada, Allen, Bradley Omron, Siemens",
    "education": "[\"Edu1\":{\"degree\":\"ITI\",\"university\":\"Govt ITI Thirukkuvalai\",\"graduationDate\":\"2000\"},\n\"Edu2\":{\"degree\":\"B. Tech\",\"university\":\"Veerbhahadursinghpurvanchal University\",\"graduationDate\":\"2014\"}]",
    "work_exp": "[{\"name\":\"AutoCAD design engineer\"},{\"name\":\"Supervisor Electrical construction\"},{\"name\":\"Electrician\"},{\"name\":\"Site supervisor\"},{\"name\":\"Site Electrician\"}]",
    "personal_info": "[\n  {\n    \"label\": \"Person\",\n    \"ID\": \"1\",\n    \"Email\": \"ad4f1u@r.postjobfree.com\"\n  }\n]",
    "volunteer_info": "No volunteer entities found in the provided resume."
}