{
    "skills": "Windows/MacOS/Linux Operating Systems, MacOS/Linux Terminal Navigation, Google Workspace, Cross Functional Collaboration, Microsoft Office 365, Jira/Freshdesk, OneLogin Administration, SW/HW Testing/Troubleshooting",
    "education": "[\"Edu1\": {\"degree\":\"Certificate of Completion: Data Analytics\", \"university\":\"Year Up, San Jose, CA\", \"graduationDate\":\"07/2020\"},\n\"Edu2\": {\"degree\":\"None Provided\", \"university\":\"Liberty High School, San Jose, CA\", \"graduationDate\":\"June 2013\"}}]",
    "work_exp": "[{\"name\":\"IT Operations Analyst\"},{\"name\":\"Intel Validation Engineering Support Technician\"},{\"name\":\"IT Technician\"},{\"name\":\"Test Engineer\"}]",
    "personal_info": "[\n    {\n        \"Name\": \"TYLER WOLFGANG VILLARREAL\",\n        \"ID\": \"100\",\n        \"Email\": \"ad4f4v@r.postjobfree.com\"\n    }\n]",
    "volunteer_info": "No volunteer work entities were found in the provided resume."
}