{
    "skills": "APEX, HTML, CSS, JAVA SCRIPT, CORE-JAVA, SQL, LWC",
    "education": "[\"Edu1\":{\"degree\":\"Bachelor of Engineering\",\"university\":\"Nandha College of Technology\",\"graduationDate\":\"****\",\"score\":\"7.5\"}]",
    "work_exp": "[{\"name\":\"Infosys Limited\"},{\"name\":\"Consultant\\nGyansys infotech\"},{\"name\":\"Software Engineer\\nTech Mahindra Pvt Limited\"}]",
    "personal_info": "[{\"Name\":\"JAMANI\",\"ID\":\"1\",\"Email\":\"ad26me@r.postjobfree.com\"}]",
    "volunteer_info": "No volunteer entities have been found in the provided resume."
}