{
    "skills": "Project Engineering, AutoCAD, Business Development, Microsoft Office, Communication, Primavera P6, Resource Planning, Material Procurement, Team Leadership, Piping Design, Risk Management, Industrial Application of Thermal Engineering, Mechanical Engineering, Project Management, Project Execution, 3D Modeling, Interdisciplinary Coordination, Project Bidding, Cost Estimation, NAVISWORKS, PDMS, CADMATIC, Autodesk Inventor, CREO, CAESAR-II E3D",
    "education": "[\"Edu1\":{\"degree\":\"MBA\",\"university\":\"University of Petroleum & Energy Studies\",\"graduationDate\":\"2019\",\"score\":\"7.05 CGPA\"},\"Edu2\":{\"degree\":\"B.E\",\"university\":\"A.I.Kalsekar Technical Campus (Mumbai University)\",\"graduationDate\":\"2017\",\"score\":\"6.15 CGPA\"},\"Edu3\":{\"degree\":\"DIPLOMA\",\"university\":\"MSBTE\",\"graduationDate\":\"2014\",\"score\":\"75.64%\"}]",
    "work_exp": "[{\"name\":\"Project Engineer \u2013 PMT BD\"},{\"name\":\"Assistant Manager\"},{\"name\":\"Engineering Consultant - Projects/Piping\"},{\"name\":\"Piping Design Engineer\"},{\"name\":\"Piping Engineer\"}]",
    "personal_info": "[{\n\"label\": \"Person\",\n\"id\": \"person1\",\n\"Name\": \"Uvais Nadir Shah\",\n\"Email\": \"ad1hei@r.postjobfree.com\"\n}]",
    "volunteer_info": "No volunteer work entities found."
}