{
    "skills": "Python, Java, Groovy, C++, C, Shell Script, CSS, HTML, SQL, MongoDB, Beautiful Soup, Scikit-learn, OpenCV, TensorFlow, Matplotlib, NumPy, Pandas, NLTK, SpaCy, UiPath, Power BI, Weka, Git, Gerrit, Gradle, Jenkins, SonarQube, WordPress, Bootstrap, Jira, Kanban, Agile, Amazon Web Services (AWS): EC2, S3, IAM, Aurora, Cloud front, VPC",
    "education": "[\n \"Edu1\": {\n  \"degree\": \"M.S in Computer Science\",\n  \"university\": \"GEORGIA STATE UNIVERSITY\",\n  \"graduationDate\": \"May 2024\",\n  \"score\": \"4.07/4.3\"\n }\n]",
    "work_exp": "[{\"name\":\"ROOFCLAIM.COM\"},{\"name\":\"GEORGIA STATE UNIVERSITY\"},{\"name\":\"TATA CONSULTANCY SERVICES\"},{\"name\":\"RESEARCH CENTRE IMARAT, DEFENCE R&D ORGANISATION OF INDIA\"}]",
    "personal_info": "[\"Name\":\"Meghana Thatikonda\",\"ID\":\"p1\",\"Email\":\"ad39yp@r.postjobfree.com\"}",
    "volunteer_info": "The provided resume does not contain any volunteer work entities."
}