{
    "skills": "Selenium WebDriver, SoapUI, Postman, Jira & MantisBt (Bug Tracking Tool), UI Automation Testing, Functional Testing, Web Application Testing, API Testing, SQL",
    "education": "No education-related information could be found in the provided resume.",
    "work_exp": "[{\"name\":\"U Gro Capital\"},{\"name\":\"Biz2Credit Info Services Pvt Ltd\"},{\"name\":\"Prolitus Web Technology\"},{\"name\":\"UG Software\"},{\"name\":\"VHS Technology Pvt ltd\"}]",
    "personal_info": "[\n  {\n    \"label\": \"Person\",\n    \"ID\": \"per001\",\n    \"Name\": \"Deepti Mundra\",\n    \"Email\": \"ad1zdu@r.postjobfree.com\"\n  }\n]",
    "volunteer_info": "No volunteer experiences were found in the resume provided."
}