{
    "skills": "Product Design & Development, Engineering Manufacturing, Engineering Analysis, Product Life Cycle Management, Research & Development, 3D Modeling & Detailing, Project & Resource Management, Engineering Change Management, Cross-functional Communication, Structural Design, Weldments design, Piping design, Wiring harness design, Creo 3.0, SolidWorks 2020, Unigraphics, Autodesk Inventor, AutoCAD 2020, Advance planning, FDM, SLS, SLA",
    "education": "[{\"Edu1\":{\"degree\":\"P.Eng\",\"university\":\"SPE\",\"graduationDate\":\"2021\"},\"Edu2\":{\"degree\":\"Fellow ship\",\"university\":\"FSIESRP\",\"graduationDate\":\"2021\"},\"Edu3\":{\"degree\":\"M.Tech\",\"university\":\"National Institute of Engineering, Mysore, Visvesvaraya Technological University, Belgaum\",\"graduationDate\":\"2015\",\"score\":\"8.40 CGPA\"},\"Edu4\":{\"degree\":\"B.E\",\"university\":\"Adichunchanagiri Institute of Technology, Chikmagalur, Visvesvaraya Technological University, Belgaum\",\"graduationDate\":\"2010\",\"score\":\"53.5%\"}}]",
    "work_exp": "[{\"name\":\"Sr. Mechanical Engineer\"},{\"name\":\"Sr. Mechanical Engineer\"},{\"name\":\"Sr. Mechanical Engineer\"},{\"name\":\"Sr. Mechanical Engineer\"},{\"name\":\"Sr. Mechanical Design Engineer\"},{\"name\":\"Mechanical Design Engineer\"}]",
    "personal_info": "[{\"Name\":\"CHANDRACHOOD BANDIGAIAH\",\"ID\":\"P1\",\"Email\":\"ad3a3x@r.postjobfree.com\"}]",
    "volunteer_info": "No volunteer work entities found in the provided resume."
}