{
    "skills": "- Project Management\n- Release / Change Management\n- Agile Methodologies\n- Product backlog / Story Mapping\n- IT Governance\n- Emotional Intelligence\n- Conflict Management\n- Team / Organization Development\n- Facilitation / Story Telling\n- Visualization Tools",
    "education": "[\"Edu1\":{\"degree\":\"Bachelor of Science\",\"university\":\"Andhra University, India (NAAC A)\",\"graduationDate\":\"2000\"},\n\"Edu2\":{\"degree\":\"Post Graduate Diploma in Business Management\",\"university\":\"Narsee Monjee Institute of Management\\nSciences, India (NAAC A+)\",\"graduationDate\":\"2019\"},\n\"Edu3\":{\"degree\":\"Master of Arts\",\"university\":\"Indira Gandhi National Open University\\n, India (NAAC A++)\",\"graduationDate\":\"2021\"}]",
    "work_exp": "[{\"name\":\"Lead Transformation Coach\"},{\"name\":\"Project Manager\"},{\"name\":\"Scrum Master\"},{\"name\":\"Release and Change Manager\"},{\"name\":\"IT \u2013 Project Manager\"},{\"name\":\"Resolution Specialist\"},{\"name\":\"Technical Support Associate\"},{\"name\":\"Scrum Master\"},{\"name\":\"Enterprise Agile Coach\"},{\"name\":\"Agile Coach\"},{\"name\":\"Scrum Master\"},{\"name\":\"Teacher\"}]",
    "personal_info": "[\n  {\n    \"id\": \"1\",\n    \"Name\": \"Vijaya Kumar\",\n    \"Email\": null\n  }\n]",
    "volunteer_info": "[{\"name\":\"Scrum buddies\"},{\"name\":\"Agile Tribe\"},{\"name\":\"Regional Scrum Gatherings\"},{\"name\":\"Pro-Bono Coaching\"},{\"name\":\"Scrum Mentoring\"},{\"name\":\"Community Involvement\"},{\"name\":\"Traffic Control Volunteer\"},{\"name\":\"Active participant in CSR Activities\"}]"
}